tcorpus/CLI_handling.py
tcorpus/__init__.py
tcorpus/__main__.py
tcorpus/cli.py
tcorpus/io_utils.py
tcorpus/main_logic.py
tcorpus/profiler.py
tcorpus-0.1.9.dist-info/METADATA
tcorpus-0.1.9.dist-info/WHEEL
tcorpus-0.1.9.dist-info/entry_points.txt
tcorpus-0.1.9.dist-info/top_level.txt
tcorpus-0.1.9.dist-info/RECORD
