Metadata-Version: 2.4
Name: tcorpus
Version: 0.1.9
Summary: A powerful CLI-based text corpus analyser for extracting palindromes, anagrams, word frequencies, pattern matches, emails, and phone numbers from text files or direct input.
Author-email: Raghu <raghu59770@gmail.com>, Santosh <padavalasantosh1@gmail.com>
Maintainer: Santosh, Raghuram
Project-URL: Homepage, https://github.com/Pegasus717/text-corpus-analyser
Project-URL: Repository, https://github.com/Pegasus717/text-corpus-analyser
Project-URL: Issues, https://github.com/Pegasus7171/text-corpus-analyser/issues
Keywords: text-analysis,corpus,nlp,cli,palindrome,anagram,word-frequency,pattern-matching,email-extraction,phone-extraction
Requires-Python: >=3.8
